<?xml version="1.0"?>

<CharacterDef xmlns:xsi="http://www.w3.org/2001/XMLSchema-instance" xmlns:xsd="http://www.w3.org/2001/XMLSchema">
    <BodyType>Dynamic</BodyType>
    <Density>1</Density>
    <FixedRotation>true</FixedRotation>
    <Fraction>0.4</Fraction>
    <Group>PlayerOne</Group>
    <Restitution>0.01</Restitution>
    <RotateZ>0</RotateZ>
    <X>-9450</X>
    <Y>700</Y>
    <UnitType>Dynamic</UnitType>
    <Alpha>1</Alpha>
    <B>1</B>
    <DrawRectangle>
        <X>0</X>
        <Y>0</Y>
        <Width>186</Width>
        <Height>181</Height>
        <Location>
            <X>0</X>
            <Y>0</Y>
        </Location>
    </DrawRectangle>
    <G>1</G>
    <R>1</R>
    <RepeatX>0</RepeatX>
    <RepeatY>0</RepeatY>
    <RotateX>0</RotateX>
    <RotateY>0</RotateY>
    <ScaleX>1</ScaleX>
    <ScaleY>1</ScaleY>
    <TexName>huawalk</TexName>
    <TransformOrigin>
        <X>0.5</X>
        <Y>0.5</Y>
    </TransformOrigin>
    <Z>101</Z>
    <ZWriteEnable>false</ZWriteEnable>
    <AI>AI\AIScripts\Patrol.py</AI>
    <Actions>
        <string>NervDog.Soul.Actions.GotHit</string>
        <string>NervDog.Soul.Actions.Attack</string>
        <string>NervDog.Soul.Actions.Dying</string>
        <string>NervDog.Soul.Actions.Walk</string>
        <string>NervDog.Soul.Actions.Jump</string>
        <string>NervDog.Soul.Actions.Stop</string>
        <string>NervDog.Soul.Actions.TurnLeft</string>
        <string>NervDog.Soul.Actions.TurnRight</string>
    </Actions>
    <FrameDefs>
        <FrameDef>
            <Name>Walk</Name>
            <DrawRectangles>
                <Rectangle>
                    <X>0</X>
                    <Y>0</Y>
                    <Width>186</Width>
                    <Height>181</Height>
                    <Location>
                        <X>0</X>
                        <Y>0</Y>
                    </Location>
                </Rectangle>
                <Rectangle>
                    <X>186</X>
                    <Y>0</Y>
                    <Width>186</Width>
                    <Height>181</Height>
                    <Location>
                        <X>186</X>
                        <Y>0</Y>
                    </Location>
                </Rectangle>
                <Rectangle>
                    <X>372</X>
                    <Y>0</Y>
                    <Width>186</Width>
                    <Height>181</Height>
                    <Location>
                        <X>372</X>
                        <Y>0</Y>
                    </Location>
                </Rectangle>
                <Rectangle>
                    <X>558</X>
                    <Y>0</Y>
                    <Width>186</Width>
                    <Height>181</Height>
                    <Location>
                        <X>558</X>
                        <Y>0</Y>
                    </Location>
                </Rectangle>
                <Rectangle>
                    <X>744</X>
                    <Y>0</Y>
                    <Width>186</Width>
                    <Height>181</Height>
                    <Location>
                        <X>744</X>
                        <Y>0</Y>
                    </Location>
                </Rectangle>
                <Rectangle>
                    <X>930</X>
                    <Y>0</Y>
                    <Width>186</Width>
                    <Height>181</Height>
                    <Location>
                        <X>930</X>
                        <Y>0</Y>
                    </Location>
                </Rectangle>
                <Rectangle>
                    <X>1117</X>
                    <Y>0</Y>
                    <Width>186</Width>
                    <Height>181</Height>
                    <Location>
                        <X>1117</X>
                        <Y>0</Y>
                    </Location>
                </Rectangle>
                <Rectangle>
                    <X>1303</X>
                    <Y>0</Y>
                    <Width>186</Width>
                    <Height>181</Height>
                    <Location>
                        <X>1303</X>
                        <Y>0</Y>
                    </Location>
                </Rectangle>
                <Rectangle>
                    <X>1489</X>
                    <Y>0</Y>
                    <Width>186</Width>
                    <Height>181</Height>
                    <Location>
                        <X>1489</X>
                        <Y>0</Y>
                    </Location>
                </Rectangle>
                <Rectangle>
                    <X>1675</X>
                    <Y>0</Y>
                    <Width>186</Width>
                    <Height>181</Height>
                    <Location>
                        <X>1675</X>
                        <Y>0</Y>
                    </Location>
                </Rectangle>
                <Rectangle>
                    <X>1861</X>
                    <Y>0</Y>
                    <Width>186</Width>
                    <Height>181</Height>
                    <Location>
                        <X>1861</X>
                        <Y>0</Y>
                    </Location>
                </Rectangle>
            </DrawRectangles>
            <FrameCount>11</FrameCount>
            <KeepTimes>
                <float>11.9999762</float>
                <float>11.9999762</float>
                <float>11.9999762</float>
                <float>11.9999762</float>
                <float>11.9999762</float>
                <float>11.9999762</float>
                <float>11.9999762</float>
                <float>11.9999762</float>
                <float>11.9999762</float>
                <float>11.9999762</float>
                <float>11.9999762</float>
            </KeepTimes>
            <Loop>false</Loop>
            <Reverse>false</Reverse>
            <Speed>3</Speed>
            <TexName>huawalk</TexName>
        </FrameDef>
        <FrameDef>
            <Name>Attack</Name>
            <DrawRectangles>
                <Rectangle>
                    <X>0</X>
                    <Y>0</Y>
                    <Width>186</Width>
                    <Height>181</Height>
                    <Location>
                        <X>0</X>
                        <Y>0</Y>
                    </Location>
                </Rectangle>
                <Rectangle>
                    <X>186</X>
                    <Y>0</Y>
                    <Width>186</Width>
                    <Height>181</Height>
                    <Location>
                        <X>186</X>
                        <Y>0</Y>
                    </Location>
                </Rectangle>
                <Rectangle>
                    <X>372</X>
                    <Y>0</Y>
                    <Width>186</Width>
                    <Height>181</Height>
                    <Location>
                        <X>372</X>
                        <Y>0</Y>
                    </Location>
                </Rectangle>
                <Rectangle>
                    <X>558</X>
                    <Y>0</Y>
                    <Width>186</Width>
                    <Height>181</Height>
                    <Location>
                        <X>558</X>
                        <Y>0</Y>
                    </Location>
                </Rectangle>
                <Rectangle>
                    <X>744</X>
                    <Y>0</Y>
                    <Width>186</Width>
                    <Height>181</Height>
                    <Location>
                        <X>744</X>
                        <Y>0</Y>
                    </Location>
                </Rectangle>
                <Rectangle>
                    <X>931</X>
                    <Y>0</Y>
                    <Width>186</Width>
                    <Height>181</Height>
                    <Location>
                        <X>931</X>
                        <Y>0</Y>
                    </Location>
                </Rectangle>
                <Rectangle>
                    <X>1117</X>
                    <Y>0</Y>
                    <Width>186</Width>
                    <Height>181</Height>
                    <Location>
                        <X>1117</X>
                        <Y>0</Y>
                    </Location>
                </Rectangle>
                <Rectangle>
                    <X>1303</X>
                    <Y>0</Y>
                    <Width>186</Width>
                    <Height>181</Height>
                    <Location>
                        <X>1303</X>
                        <Y>0</Y>
                    </Location>
                </Rectangle>
                <Rectangle>
                    <X>1489</X>
                    <Y>0</Y>
                    <Width>186</Width>
                    <Height>181</Height>
                    <Location>
                        <X>1489</X>
                        <Y>0</Y>
                    </Location>
                </Rectangle>
            </DrawRectangles>
            <FrameCount>9</FrameCount>
            <KeepTimes>
                <float>11.9999762</float>
                <float>11.9999762</float>
                <float>11.9999762</float>
                <float>11.9999762</float>
                <float>11.9999762</float>
                <float>11.9999762</float>
                <float>11.9999762</float>
                <float>11.9999762</float>
                <float>11.9999762</float>
            </KeepTimes>
            <Loop>false</Loop>
            <Reverse>true</Reverse>
            <Speed>12</Speed>
            <TexName>huaattack</TexName>
        </FrameDef>
        <FrameDef>
            <Name>Jump</Name>
            <DrawRectangles>
                <Rectangle>
                    <X>0</X>
                    <Y>0</Y>
                    <Width>186</Width>
                    <Height>181</Height>
                    <Location>
                        <X>0</X>
                        <Y>0</Y>
                    </Location>
                </Rectangle>
            </DrawRectangles>
            <FrameCount>1</FrameCount>
            <KeepTimes>
                <float>11.9999762</float>
            </KeepTimes>
            <Loop>false</Loop>
            <Reverse>false</Reverse>
            <Speed>1</Speed>
            <TexName>huawalk</TexName>
        </FrameDef>
    </FrameDefs>
    <HP>10</HP>
    <Height>181</Height>
    <MaxHP>10</MaxHP>
    <MoveSpeed>
        <X>300</X>
        <Y>600</Y>
    </MoveSpeed>
    <Width>90</Width>
    <Damage>2</Damage>
    <SoundEffects>
        <KeyValuePair>
            <Key>Attack</Key>
            <Value>mao</Value>
        </KeyValuePair>
    </SoundEffects>
</CharacterDef>